tscat/__init__.py
tscat/base.py
tscat/filtering.py
tscat/import_export.py
tscat/py.typed
tscat/orm_sqlalchemy/__init__.py
tscat/orm_sqlalchemy/alembic.ini
tscat/orm_sqlalchemy/orm.py
tscat/orm_sqlalchemy/migrations/README
tscat/orm_sqlalchemy/migrations/env.py
tscat/orm_sqlalchemy/migrations/script.py.mako
tscat/orm_sqlalchemy/migrations/versions/0c057a8951ba_initial_migration.py
tscat/orm_sqlalchemy/migrations/versions/9a655086fb51_add_rating_field_to_event.py
tscat-0.4.4.dist-info/licenses/LICENSE
tscat-0.4.4.dist-info/WHEEL
tscat-0.4.4.dist-info/METADATA
tscat-0.4.4.dist-info/RECORD
